odoo/addons/contract_variable_qty_sale_order_line/README.rst
odoo/addons/contract_variable_qty_sale_order_line/__init__.py
odoo/addons/contract_variable_qty_sale_order_line/__manifest__.py
odoo/addons/contract_variable_qty_sale_order_line/data/contract_variable_qty_sale_order_line.xml
odoo/addons/contract_variable_qty_sale_order_line/i18n/contract_variable_qty_sale_order_line.pot
odoo/addons/contract_variable_qty_sale_order_line/readme/CONTRIBUTORS.rst
odoo/addons/contract_variable_qty_sale_order_line/readme/CREDITS.rst
odoo/addons/contract_variable_qty_sale_order_line/readme/DESCRIPTION.rst
odoo/addons/contract_variable_qty_sale_order_line/readme/USAGE.rst
odoo/addons/contract_variable_qty_sale_order_line/static/description/banner.png
odoo/addons/contract_variable_qty_sale_order_line/static/description/icon.png
odoo/addons/contract_variable_qty_sale_order_line/static/description/index.html
odoo12_addon_contract_variable_qty_sale_order_line-12.0.1.0.0.99.dev3.dist-info/METADATA
odoo12_addon_contract_variable_qty_sale_order_line-12.0.1.0.0.99.dev3.dist-info/WHEEL
odoo12_addon_contract_variable_qty_sale_order_line-12.0.1.0.0.99.dev3.dist-info/top_level.txt
odoo12_addon_contract_variable_qty_sale_order_line-12.0.1.0.0.99.dev3.dist-info/RECORD
