Metadata-Version: 2.1
Name: odoo12-addon-contract-variable-qty-sale-order-line
Version: 12.0.1.0.0.99.dev3
Summary: This module adds a formula to compute sale order line quantity to invoice as extension of the module contract_variable_quantity
Home-page: https://github.com/OCA/contract
Author: Escodoo,Odoo Community Association (OCA)
Author-email: support@odoo-community.org
License: AGPL-3
Platform: UNKNOWN
Classifier: Programming Language :: Python
Classifier: Framework :: Odoo
Classifier: Framework :: Odoo :: 12.0
Classifier: License :: OSI Approved :: GNU Affero General Public License v3
Requires-Python: >=3.5
Requires-Dist: odoo12-addon-product-contract-variable-quantity
Requires-Dist: odoo <12.1dev,>=12.0a
